setup.py
virtualenvwrapper/__init__.py
virtualenvwrapper/github.py
virtualenvwrapper.github.egg-info/PKG-INFO
virtualenvwrapper.github.egg-info/SOURCES.txt
virtualenvwrapper.github.egg-info/dependency_links.txt
virtualenvwrapper.github.egg-info/entry_points.txt
virtualenvwrapper.github.egg-info/namespace_packages.txt
virtualenvwrapper.github.egg-info/not-zip-safe
virtualenvwrapper.github.egg-info/requires.txt
virtualenvwrapper.github.egg-info/top_level.txt