Metadata-Version: 1.0
Name: virtualenvwrapper.github
Version: 0.1.2
Summary: Plugin for virtualenvwrapper to automatically create projects based on github repositories.
Home-page: http://github.com/jmcantrell/virtualenvwrapper.github/
Author: Jeremy Cantrell
Author-email: jmcantrell@gmail.com
License: UNKNOWN
Download-URL: http://github.com/jmcantrell/virtualenvwrapper.github/tarball/0.1.2
Platform: Any
Classifier: Development Status :: 4 - Beta
Classifier: License :: OSI Approved :: BSD License
Classifier: Programming Language :: Python
Classifier: Intended Audience :: Developers
Classifier: Environment :: Console
